migdalor-0.0.3.dist-info/METADATA
migdalor-0.0.3.dist-info/WHEEL
migdalor-0.0.3.dist-info/licenses/LICENSE
migdalor/__init__.py
migdalor/__version__.py
migdalor/cluster.py
migdalor/discovery.py
migdalor/logger.py
migdalor/py.typed
migdalor-0.0.3.dist-info/RECORD
