Metadata-Version: 2.1
Name: migdalor
Version: 0.0.3
Summary: A cluster membership library for modern asyncio Python distributed systems running in Kubernetes
Keywords: peer discovery kubernetes service-discovery cluster-membership-management
Author-Email: Roman Glushko <roman.glushko.m@gmail.com>
License: MIT
Classifier: Development Status :: 4 - Beta
Classifier: Environment :: Web Environment
Classifier: Operating System :: OS Independent
Classifier: Intended Audience :: Developers
Classifier: Programming Language :: Python :: 3
Classifier: Programming Language :: Python :: 3.9
Classifier: Programming Language :: Python :: 3.10
Classifier: Programming Language :: Python :: 3.11
Classifier: License :: OSI Approved :: MIT License
Classifier: Topic :: System :: Networking
Classifier: Typing :: Typed
Project-URL: Homepage, https://github.com/roma-glushko/migdalor
Project-URL: Source, https://github.com/roma-glushko/migdalor
Requires-Python: >=3.9
